smmap/__init__.py
smmap/buf.py
smmap/exc.py
smmap/mman.py
smmap/util.py
smmap/test/__init__.py
smmap/test/lib.py
smmap/test/test_buf.py
smmap/test/test_mman.py
smmap/test/test_tutorial.py
smmap/test/test_util.py
smmap2-2.0.4.dist-info/METADATA
smmap2-2.0.4.dist-info/RECORD
smmap2-2.0.4.dist-info/WHEEL
smmap2-2.0.4.dist-info/top_level.txt
smmap2-2.0.4.dist-info/zip-safe
